{
  "fields": {
    "type": {
      "options": ["local", "digitalOceanSpaces"]
    },
    "connection": {
      "type": "link",
      "tooltip": true,
      "view": "views/fields/link",
      "conditionalProperties": {
        "visible": {
          "conditionGroup": [
            {
              "type": "in",
              "attribute": "type",
              "value": ["digitalOceanSpaces"]
            }
          ]
        },
        "required": {
          "conditionGroup": [
            {
              "type": "in",
              "attribute": "type",
              "value": ["digitalOceanSpaces"]
            }
          ]
        }
      }
    },

    "doPathPrefix": { "type": "varchar", "default": "" },
    "doCdnEndpoint": { "type": "varchar", "tooltip": true },

    "syncEnabled": { "type": "bool", "default": false, "tooltip": true },
    "syncDirection": {
      "type": "enum",
      "options": ["upload", "download", "both"],
      "default": "upload",
      "tooltip": true
    },
    "syncOnFileSave": { "type": "bool", "default": true, "tooltip": true },
    "syncDeleteRemote": { "type": "bool", "default": false, "tooltip": true },
    "lastSyncAt": { "type": "datetime", "readOnly": true },
    "lastSyncStatus": { "type": "varchar", "readOnly": true }
  },
  "links": {
    "connection": {
      "type": "belongsTo",
      "entity": "Connection",
      "foreign": "storages"
    }
  }
}
